README.rst
setup.py
lipy_notify/__init__.py
lipy_notify/lipy_notify.py
lipy_notify.egg-info/PKG-INFO
lipy_notify.egg-info/SOURCES.txt
lipy_notify.egg-info/dependency_links.txt
lipy_notify.egg-info/requires.txt
lipy_notify.egg-info/top_level.txt