Metadata-Version: 1.1
Name: lipy-notify
Version: 1.0
Summary: Post message to LINE.app from python
Home-page: https://github.com/butsugiri
Author: shunk52
Author-email: shunk52@gmail.com
License: MIT
Platform: UNKNOWN
Classifier: Programming Language :: Python :: 2
Classifier: Programming Language :: Python :: 2.7
Classifier: License :: OSI Approved :: MIT License
